[
    {
        "id": 1,
        "code": "001",
        "name": "Taboo List",
        "active": 1,
        "date_start": "2019-04-20",
        "cards": [
            {
                "code": "01020",
                "xp": 2
            },
            {
                "code": "01050",
                "xp": 2
            },
            {
                "code": "02152",
                "xp": 1
            },
            {
                "code": "02187",
                "xp": 5
            },
            {
                "code": "02189",
                "xp": 5
            },
            {
                "code": "02193",
                "xp": 2
            },
            {
                "code": "01033",
                "text": "This card’s [reaction] ability now reads: “After you successfully investigate, exhaust Dr. Milan Christopher…”"
            },
            {
                "code": "02002",
                "text": "This card’s [reaction] ability gains: “(Limit once per round.)”"
            },
            {
                "code": "02111",
                "text": "This card gains: “Group limit 2 copies of Delve Too Deep in the victory display.”"
            },
            {
                "code": "02229",
                "text": "This card gains: “Max 1 committed per skill test.”"
            },
            {
                "code": "02266",
                "text": "This card gains: “Max once per round.”"
            },
            {
                "code": "03029",
                "text": "This card’s ability now reads: “Put an [[Item]] asset that takes up fewer than 2 hand slots into play from your hand.”"
            },
            {
                "code": "03315",
                "exceptional": true,
                "text": "This card gains the Exceptional keyword."
            }
        ]
    },
    {
        "id": 2,
        "code": "002",
        "name": "Taboo List",
        "active": 1,
        "date_start": "2019-09-27",
        "cards": [
            {
                "code": "01020",
                "xp": 2
            },
            {
                "code": "01050",
                "xp": 2
            },
            {
                "code": "02026",
                "xp": 3
            },
            {
                "code": "02152",
                "xp": 1
            },
            {
                "code": "02187",
                "xp": 5
            },
            {
                "code": "02189",
                "xp": 5
            },
            {
                "code": "02193",
                "xp": 2
            },
            {
                "code": "02226",
                "xp": -1
            },
            {
                "code": "05159",
                "xp": 3
            },
            {
                "code": "01033",
                "text": "This card’s [reaction] ability now reads: “After you successfully investigate, exhaust Dr. Milan Christopher…”"
            },
            {
                "code": "02002",
                "text": "This card’s [reaction] ability gains: “(Limit once per round.)”"
            },
            {
                "code": "02111",
                "text": "This card gains: “Group limit 2 copies of Delve Too Deep in the victory display.”"
            },
            {
                "code": "02229",
                "text": "This card gains: “Max 1 committed per skill test.”"
            },
            {
                "code": "02266",
                "text": "This card gains: “Max once per round.”"
            },
            {
                "code": "03029",
                "text": "This card’s ability now reads: “Put an [[Item]] asset that takes up fewer than 2 hand slots into play from your hand.”"
            },
            {
                "code": "03315",
                "exceptional": true,
                "text": "This card gains the Exceptional keyword."
            }
        ]
    },
    {
        "id": 3,
        "code": "003",
        "name": "Taboo List",
        "active": 1,
        "date_start": "2020-10-15",
        "cards": [
            {
                "code": "01020",
                "xp": 1
            },
            {
                "code": "01050",
                "xp": 2
            },
            {
                "code": "02108",
                "xp": 2
            },
            {
                "code": "02152",
                "xp": 1
            },
            {
                "code": "02187",
                "xp": 3
            },
            {
                "code": "02189",
                "xp": 3
            },
            {
                "code": "02193",
                "xp": 1
            },
            {
                "code": "02226",
                "xp": -1
            },
            {
                "code": "04305",
                "xp": 1
            },
            {
                "code": "05153",
                "xp": 4
            },
            {
                "code": "05159",
                "xp": 3
            },
            {
                "code": "05231",
                "xp": 2
            },
            {
                "code": "06021",
                "xp": 3
            },
            {
                "code": "60233",
                "xp": 3
            },
            {
                "code": "01033",
                "text": "This card’s [reaction] ability now reads: “After you successfully investigate, exhaust Dr. Milan Christopher…”"
            },
            {
                "code": "02002",
                "text": "This card’s [reaction] ability gains: “(Limit once per round.)”"
            },
            {
                "code": "02111",
                "text": "This card gains: “Group limit 2 copies of Delve Too Deep in the victory display.”"
            },
            {
                "code": "02229",
                "text": "At the end of its ability, this card gains: “(max once per round).”"
            },
            {
                "code": "02266",
                "text": "This card gains: “Max once per round.”"
            },
            {
                "code": "03029",
                "text": "This card’s ability now reads: “Put a level 0-3 [[Item]] asset into play from your hand.”"
            },
            {
                "code": "03315",
                "exceptional": true,
                "text": "This card gains the Exceptional keyword."
            },
            {
                "code": "04309",
                "text": "At the end of its ability, this card gains: “Remove All In from the game.”"
            },
            {
                "code": "05116",
                "text": "This card’s [action] ability is now a [fast] ability."
            },
            {
                "code": "05188",
                "text": "This card’s [action] ability is now a [fast] ability."
            },
            {
                "code": "05189",
                "text": "This card’s [action] ability is now a [fast] ability."
            },
            {
                "code": "06195",
                "text": "This card’s [action] ability now reads: “[action] Spend 1 ammo: <b>Fight.</b> You get +2 [combat] for this attack. If a chaos token with a non-negative modifier is revealed during this attack, this attack deals +2 damage.”"
            },
            {
                "code": "02026",
                "deck_limit": 0,
                "text": "Forbidden."
            }
        ]
    },
    {
        "id": 4,
        "code": "004",
        "name": "Taboo List",
        "active": 1,
        "date_start": "2021-06-26",
        "cards": [
            {
                "code": "01020",
                "xp": 1
            },
            {
                "code": "01050",
                "text": "This card now reads: “Disengage from each enemy engaged with you and move to a connecting location with no enemies.”"
            },
            {
                "code": "02108",
                "xp": 2
            },
            {
                "code": "02152",
                "xp": 1
            },
            {
                "code": "02187",
                "xp": 3
            },
            {
                "code": "02189",
                "xp": 3
            },
            {
                "code": "02193",
                "xp": 1
            },
            {
                "code": "02226",
                "text": "This card’s [action] ability gains: “This attack may target a non-[[Elite]] enemy up to one location away from its standard range, ignoring the aloof and retaliate keywords.”"
            },
            {
                "code": "04305",
                "xp": 1
            },
            {
                "code": "05153",
                "xp": 4
            },
            {
                "code": "05159",
                "xp": 3
            },
            {
                "code": "05230",
                "text": "This card loses the text: “Attached asset cannot be used to attack enemies engaged with you.”"
            },
            {
                "code": "05231",
                "xp": 2
            },
            {
                "code": "05324",
                "text": "This card’s ability gains: “Remove Eucatastrophe from the game.”"
            },
            {
                "code": "06022",
                "text": "This card’s constant ability now reads: “If this card has no charges, remove it from the game.”"
            },
            {
                "code": "06199",
                "text": "This card’s ability gains: “Remove each committed copy of Three Aces from the game.”"
            },
            {
                "code": "60233",
                "xp": 3
            },
            {
                "code": "07269",
                "text": "This card’s ability gains: “Remove A Watchful Peace from the game.”"
            },
            {
                "code": "07301",
                "text": "This card’s ability gains: “Remove Hallow from the game.”"
            },
            {
                "code": "01033",
                "text": "This card’s [reaction] ability now reads: “After you successfully investigate, exhaust Dr. Milan Christopher…”"
            },
            {
                "code": "02002",
                "text": "This card’s [reaction] ability gains: “(Limit once per round.)”"
            },
            {
                "code": "02111",
                "text": "This card gains: “Group limit 2 copies of Delve Too Deep in the victory display.”"
            },
            {
                "code": "02229",
                "text": "At the end of its ability, this card gains: “(max once per round).”"
            },
            {
                "code": "02266",
                "text": "This card gains: “Max once per round.”"
            },
            {
                "code": "03029",
                "text": "This card’s ability now reads: “Put a level 0-3 [[Item]] asset into play from your hand.”"
            },
            {
                "code": "03315",
                "exceptional": true,
                "text": "This card gains the Exceptional keyword."
            },
            {
                "code": "04309",
                "text": "At the end of its ability, this card gains: “Remove All In from the game.”"
            },
            {
                "code": "05116",
                "text": "This card’s [action] ability is now a [fast] ability."
            },
            {
                "code": "05188",
                "text": "This card’s [action] ability is now a [fast] ability."
            },
            {
                "code": "05189",
                "text": "This card’s [action] ability is now a [fast] ability."
            },
            {
                "code": "06195",
                "text": "This card’s [action] ability now reads: “[action] Spend 1 ammo: <b>Fight.</b> You get +2 [combat] for this attack. If a chaos token with a non-negative modifier is revealed during this attack, this attack deals +2 damage.”"
            },
            {
                "code": "02026",
                "deck_limit": 0,
                "text": "Forbidden."
            }
        ]
    },
    {
        "id": 5,
        "code": "005",
        "name": "Taboo List",
        "active": 1,
        "date_start": "2022-08-28",
        "cards": [
            {
                "code": "01050",
                "text": "This card now reads: “Disengage from each enemy engaged with you and move to a connecting location with no enemies.”"
            },
            {
                "code": "02108",
                "xp": 2
            },
            {
                "code": "02152",
                "xp": 1
            },
            {
                "code": "02187",
                "xp": 3
            },
            {
                "code": "02189",
                "xp": 3
            },
            {
                "code": "02193",
                "xp": 1
            },
            {
                "code": "02226",
                "text": "This card’s [action] ability gains: “This attack may target a non-[[Elite]] enemy up to one location away from its standard range, ignoring the aloof and retaliate keywords.”"
            },
            {
                "code": "04305",
                "xp": 1
            },
            {
                "code": "05153",
                "text": "This card’s [fast] ability is now a [action] ability."
            },
            {
                "code": "05159",
                "xp": 3
            },
            {
                "code": "05230",
                "text": "This card loses the text: “Attached asset cannot be used to attack enemies engaged with you.”"
            },
            {
                "code": "05231",
                "xp": 2
            },
            {
                "code": "05324",
                "text": "This card’s ability gains: “Remove Eucatastrophe from the game.”"
            },
            {
                "code": "06022",
                "text": "This card’s constant ability now reads: “If this card has no charges, remove it from the game.”"
            },
            {
                "code": "06199",
                "text": "This card’s ability gains: “Remove each committed copy of Three Aces from the game.”"
            },
            {
                "code": "60233",
                "xp": 3
            },
            {
                "code": "03112",
                "xp": 3
            },
            {
                "code": "07197",
                "xp": -2
            },
            {
                "code": "07308",
                "xp": -2
            },
            {
                "code": "08032",
                "xp": 2
            },
            {
                "code": "08099",
                "xp": 2
            },
            {
                "code": "07269",
                "text": "This card’s ability gains: “Remove A Watchful Peace from the game.”"
            },
            {
                "code": "07301",
                "text": "This card’s ability gains: “Remove Hallow from the game.”"
            },
            {
                "code": "01033",
                "text": "This card’s [reaction] ability now reads: “After you successfully investigate, exhaust Dr. Milan Christopher…”"
            },
            {
                "code": "02002",
                "text": "This card’s [reaction] ability gains: “(Limit once per round.)”"
            },
            {
                "code": "02111",
                "text": "This card gains: “Group limit 2 copies of Delve Too Deep in the victory display.”"
            },
            {
                "code": "02229",
                "text": "At the end of its ability, this card gains: “(max once per round).”"
            },
            {
                "code": "02266",
                "text": "This card gains: “Max once per round.”"
            },
            {
                "code": "03029",
                "text": "This card’s ability now reads: “Put a level 0-3 [[Item]] asset into play from your hand.”"
            },
            {
                "code": "03315",
                "exceptional": true,
                "text": "This card gains the Exceptional keyword."
            },
            {
                "code": "04309",
                "text": "At the end of its ability, this card gains: “Remove All In from the game.”"
            },
            {
                "code": "05116",
                "text": "This card’s [action] ability is now a [fast] ability."
            },
            {
                "code": "05188",
                "text": "This card’s [action] ability is now a [fast] ability."
            },
            {
                "code": "05189",
                "text": "This card’s [action] ability is now a [fast] ability."
            },
            {
                "code": "06195",
                "text": "This card’s [action] ability now reads: “[action] Spend 1 ammo: <b>Fight.</b> You get +2 [combat] for this attack. If a chaos token with a non-negative modifier is revealed during this attack, this attack deals +2 damage.”"
            },
            {
                "code": "02026",
                "deck_limit": 0,
                "text": "Forbidden."
            },
            {
                "code": "02029",
                "text": "This card now reads \"a symbol\" instead of the list of indicated symbols."
            },
            {
                "code": "02269",
                "text": "This card now reads \"a symbol\" instead of the list of indicated symbols."
            },
            {
                "code": "60416",
                "text": "This card now reads \"a symbol\" instead of the list of indicated symbols."
            },
            {
                "code": "02263",
                "text": "This card's fight ability now reads \"+1 damage\" instead of \"+2 damage.\""
            },
            {
                "code": "03006",
                "text": "This card's forced ability is moved to its reverse side, and it should now read: \"<b>Additional Setup</b>: After you draw your opening hand, choose a role ([survivor], [guardian], [seeker], [rogue], [mystic], or Neutral).\" This card's front side additionally gains: \"[action]: Switch roles. Does not provoke attacks of opportunity.\""
            },
            {
                "code": "03019",
                "text": "This card's revelation ability now reads: \"Discard 1 card in your hand or play area of your current role. Then...\""
            },
            {
                "code": "04032",
                "text": "This card now reads \"a non-[elder_sign] symbol\" instead of \"a [skull], [cultist], [tablet], [elder_thing], or [auto_fail] symbol.\""
            },
            {
                "code": "04110",
                "text": "This card now reads \"a non-[auto_fail] symbol\" instead of \"a [skull], [cultist], [tablet], or [elder_thing] chaos token.\""
            },
            {
                "code": "06002",
                "text": "This investigator now reads: \"Deck Size: 50\" and \"Deckbuilding Requirements (do not count towards deck size): 3 copies of Occult Evidence...\"",
                "deck_options": [
                    {
                        "faction": ["seeker","neutral"],
                        "level": { "min":0,"max":5 }
                    },
                    {
                        "name": "Secondary Class",
                        "faction_select": ["mystic","rogue","survivor"],"level": { "min":0,"max":1 },
                        "type":["event","skill"],
                        "limit":10
                    }
                ],
                "deck_requirements":{
                    "size": 50,
                    "card": {
                        "06008": { "06008": "06008" },
                        "06009": { "06009": "06009" }
                    },
                    "random":[
                        {
                            "target":"subtype",
                            "value":"basicweakness"
                        }
                    ]
                }
            },
            {
                "code": "07268",
                "exceptional": false,
                "deck_limit": 1,
                "text": "This card loses the exceptional keyword and gains \"Limit 1 per deck.\""
            },
            {
                "code": "08045",
                "text": "This card's constant ability now reads: \"...you get +1 [intellect], +1 [agility], and ignore the first attack of opportunity you take each turn.\""
            },
            {
                "code": "08055",
                "text": "This card gains: “Max once per round.”"
            },
            {
                "code": "08098",
                "text": "This card should read \"following basic actions\" instead of \"following actions.\""
            },
            {
                "code": "08100",
                "text": "This card should read \"following basic actions\" instead of \"following actions.\""
            },
            {
                "code": "08093",
                "text": "This card's parenthetical now reads: \"...(If you succeed by 3 or more, you may exhaust Cyclopean Hammer to instead deal +2 damage and move the enemy up to two locations away from you.)\""
            }
        ]
    }
]
