{
  "torch": "El encuentro",
  "arkham": "Las máscaras de medianoche",
  "cultists": "Secta de Umôrdhoth",
  "tentacles": "El Devorador de las Profundidades",
  "rats": "Ratas",
  "ghouls": "Gules",
  "striking_fear": "Miedo impactante",
  "ancient_evils": "Antiguos males",
  "chilling_cold": "Frío helador",
  "pentagram": "Secta oscura",
  "nightgaunts": "Ángeles descarnados",
  "locked_doors": "Puertas cerradas",
  "agents_of_hastur": "Agentes de Hastur",
  "agents_of_yog": "Agentes de Yog-Sothoth",
  "agents_of_shub": "Agentes de Shub-Niggurath",
  "agents_of_cthulhu": "Agentes de Cthulhu",
  "unknown": "Desconocido",
  "bayou": "El bayou",
  "rougarou": "La maldición del Rougarou",
  "venice": "Venecia",
  "armitages_fate": "El destino de Armitage",
  "bishops_thralls": "Esclavos de Bishop",
  "beast_thralls": "Esclavos-bestia",
  "naomis_crew": "La banda de Naomi",
  "extracurricular_activity": "Actividad extracurricular",
  "the_house_always_wins": "La casa siempre gana",
  "sorcery": "Hechicería",
  "dunwich": "Dunwich",
  "whippoorwills": "Chotacabras",
  "bad_luck": "Mala suerte",
  "the_beyond": "Más allá",
  "hideous_abominations": "Abominaciones espantosas",
  "the_miskatonic_museum": "El museo Miskatonic",
  "essex_county_express": "El Essex County Express",
  "blood_on_the_altar": "Sangre en el altar",
  "undimensioned_and_unseen": "Invisibles y sin dimensión",
  "where_doom_awaits": "Donde aguarda la perdición",
  "lost_in_time_and_space": "Perdidos en el tiempo y el espacio",
  "curtain_call": "Se cierra el telón",
  "the_last_king": "El último rey",
  "delusions": "Delirios",
  "byakhee": "Byakhee",
  "inhabitants_of_carcosa": "Habitantes de Carcosa",
  "evil_portents": "Portentos malignos",
  "hauntings": "Apariciones",
  "hasturs_gift": "El regalo de Hastur",
  "cult_of_the_yellow_sign": "Secta del Signo Amarillo",
  "decay": "Podredumbre e impurezas",
  "stranger": "El extranjero",
  "echoes_of_the_past": "Ecos del pasado",
  "the_unspeakable_oath": "El juramento inconfesable",
  "a_phantom_of_truth": "El fantasma de la verdad",
  "the_pallid_mask": "La máscara pálida",
  "black_stars_rise": "Surgen estrellas negras",
  "flood": "La inundación de abajo",
  "vortex": "El vórtice de arriba",
  "dim_carcosa": "Penumbrosa Carcosa",
  "agents_of_yig": "Agentes de Yig",
  "traps": "Trampas letales",
  "expedition": "Expedición",
  "ruins": "Ruinas olvidadas",
  "guardians_of_time": "Guardianes del tiempo",
  "pnakotic_brotherhood": "Hermandad pnakótica",
  "poison": "Veneno",
  "rainforest": "Selva",
  "serpents": "Serpientes",
  "flux": "Flujo temporal",
  "eztli": "La perdición de Eztli",
  "wilds": "Naturaleza salvaje",
  "venom": "Ponzoña de Yig",
  "threads_of_fate": "Los hilos del destino",
  "the_boundary_beyond": "El límite del otro lado",
  "heart_of_the_elders": "El corazón de los ancianos",
  "pillars_of_judgment": "Columnas del juicio",
  "knyan": "K'n-yan",
  "the_city_of_archives": "La Ciudad de los Archivos",
  "the_depths_of_yoth": "Las profundidades de Yoth",
  "shattered_aeons": "Eones destrozados",
  "turn_back_time": "Vuelta atrás en el tiempo",
  "agents_of_azathoth": "Agentes de Azathoth",
  "anettes_coven": "Aquelarre de Anette",
  "at_deaths_doorstep": "A las puertas de la muerte",
  "city_of_sins": "Ciudad de pecados",
  "disappearance_at_the_twilight_estate": "Desaparición en la finca del Crepúsculo",
  "inexorable_fate": "Destino inexorable",
  "realm_of_death": "El reino de la muerte",
  "silver_twilight_lodge": "Logia del Crepúsculo de Plata",
  "spectral_predators": "Depredadores espectrales",
  "the_watcher": "El vigilante",
  "the_witching_hour": "La hora bruja",
  "trapped_spirits": "Espíritus atrapados",
  "witchcraft": "Brujería",
  "the_secret_name": "El nombre secreto",
  "the_wages_of_sin": "La paga del pecado",
  "for_the_greater_good": "Por el bien común",
  "union_and_disillusion": "Unión y desilusión",
  "in_the_clutches_of_chaos": "En las garras del caos",
  "music_of_the_damned": "Música de los condenados",
  "secrets_of_the_universe": "Secretos del universo",
  "before_the_black_throne": "Ante el trono negro",
  "agents_of_atlach_nacha": "Agentes de Atlach-Nacha",
  "agents_of_nyarlathotep": "Agentes de Nyarlathotep",
  "corsairs": "Corsarios",
  "creatures_of_the_underworld": "Criaturas del Mundo subterráneo",
  "dreamers_curse": "Maldición del soñador",
  "dreamlands": "Tierras del Sueño",
  "merging_realities": "Realidades mezcladas",
  "spiders": "Arañas",
  "whispers_of_hypnos": "Susurros de Hipnos",
  "zoogs": "Zoogs",
  "in_the_labyrinths_of_lunacy": "Los laberintos de la demencia",
  "epic_multiplayer": "Multijugador épico",
  "single_group": "Grupo único",
  "abyssal_gifts": "Regalos abisales",
  "abyssal_tribute": "Tributo abisal",
  "brotherhood_of_the_beast": "La Hermandad de la bestia",
  "sands_of_egypt": "Arenas de Egipto",
  "the_eternal_slumber": "El letargo eterno",
  "the_nights_usurper": "El usurpador de la noche",
  "return_to_the_gathering": "Regreso a El encuentro",
  "return_to_the_midnight_masks": "Regreso a Las máscaras a medianoche",
  "return_to_the_devourer_below": "Regreso al Devorador de las Profundidades",
  "ghouls_of_umôrdhoth": "Gules de Umôrdhoth",
  "the_devourers_cult": "La secta del Devorador",
  "return_cult": "Secta de Umôrdhoth",
  "return_to_extracurricular_activities": "Regreso a Actividades extracurriculares",
  "return_to_the_house_always_wins": "Regreso a La casa siempre gana",
  "return_to_the_miskatonic_museum": "Regreso al Museo Miskatonic",
  "return_to_the_essex_county_express": "Regreso a el Essex County Express",
  "return_to_blood_on_the_altar": "Regreso a Sangre en el altar",
  "return_to_undimensioned_and_unseen": "Regreso a Invisibles y sin dimensión",
  "return_to_where_doom_awaits": "Regreso a Donde aguarda la perdición",
  "return_to_lost_in_time_and_space": "Regreso a Perdidos en el tiempo y el espacio",
  "resurgent_evils": "Males renacientes",
  "erratic_fear": "Miedo errático",
  "creeping_cold": "Frío insidioso",
  "secret_doors": "Puertas secretas",
  "yog_sothoths_emissaries": "Emisarios de Yog-Sothoth",
  "beyond_the_threshold": "Más allá del umbral",
  "return_to_curtain_call": "Regreso a Se cierra el telón",
  "return_to_the_last_king": "Regreso a El último rey",
  "return_to_echoes_of_the_past": "Regreso a Ecos del pasado",
  "return_to_the_unspeakable_oath": "Regreso a El juramento inconfesable",
  "return_to_a_phantom_of_truth": "Regreso a El fantasma de la verdad",
  "return_to_the_pallid_mask": "Regreso a La máscara pálida",
  "return_to_black_stars_rise": "Regreso a Surgen estrellas negras",
  "return_to_dim_carcosa": "Regreso a Penumbrosa Carcosa",
  "delusory_evils": "Males ilusorios",
  "neurotic_fear": "Miedo neurótico",
  "hasturs_envoys": "Enviados de Hastur",
  "decaying_reality": "Realidad putrefacta",
  "maddening_delusions": "Delirios enloquecedores",
  "beyond_the_gates_of_sleep": "Más allá de las Puertas del Sueño",
  "waking_nightmare": "Pesadilla consciente",
  "a_thousand_shapes_of_horror": "Mil formas de horror",
  "the_search_for_kadath": "La búsqueda de Kadath",
  "dark_side_of_the_moon": "El lado oscuro de la Luna",
  "point_of_no_return": "Punto sin retorno",
  "where_the_gods_dwell": "Donde moran los dioses",
  "weaver_of_the_cosmos": "Tejedora del cosmos",
  "terror_of_the_vale": "Terror of the Vale",
  "descent_into_the_pitch": "Descenso a la brea",
  "murder_at_the_excelsior_hotel": "Asesinato en el hotel Excelsior",
  "alien_interference": "Interferencia alienígena",
  "dark_rituals": "Rituales oscuros",
  "excelsior_management": "Dirección del Excelsior",
  "sins_of_the_past": "Pecados del pasado",
  "vile_experiments": "Experimentos viles",
  "blob": "La masa que lo devoraba todo",
  "blob_epic_multiplayer": "Multijugador épico",
  "blob_single_group": "Grupo único",
  "migo_incursion": "Incursión mi-go",
  "read_or_die": "Lee o muere",
  "all_or_nothing": "All or Nothing",
  "return_to_the_untamed_wilds": "Return to the Untamed Wilds",
  "return_to_the_doom_of_eztli": "Regreso a La maldición de Eztli",
  "return_to_threads_of_fate": "Regreso a Los hilos del destino",
  "return_to_the_boundary_beyond": "Regreso a El límite del otro lado",
  "return_to_heart_of_the_elders": "Regreso a El corazón de los ancianos",
  "return_to_pillars_of_judgment": "Regreso a las Columnas del juicio",
  "return_to_knyan": "Regreso a K'n-yan",
  "return_to_the_city_of_archives": "Regreso a La Ciudad de los Archivos",
  "return_to_the_depths_of_yoth": "Regreso a Las profundidades de Yoth",
  "return_to_shattered_aeons": "Regreso a Eones destrozados",
  "return_to_turn_back_time": "Regreso a Vuelta atrás en el tiempo",
  "return_to_the_rainforest": "Regreso a la Selva",
  "cult_of_pnakotus": "Cult of Pnakotus",
  "doomed_expedition": "Doomed Expedition",
  "temporal_hunters": "Temporal Hunters",
  "venomous_hate": "Venomous Hate"
}